bioimage_embed/__init__.py
bioimage_embed/augmentations.py
bioimage_embed/bie.py
bioimage_embed/cli.py
bioimage_embed/config.py
bioimage_embed/datasets/__init__.py
bioimage_embed/datasets.py
bioimage_embed/hydra.py
bioimage_embed/inference.py
bioimage_embed/lightning/__init__.py
bioimage_embed/lightning/dataloader.py
bioimage_embed/lightning/pyro.py
bioimage_embed/lightning/tests/__init__.py
bioimage_embed/lightning/tests/test_contrastive_learning.py
bioimage_embed/lightning/tests/test_ndims.py
bioimage_embed/lightning/torch.py
bioimage_embed/models/__init__.py
bioimage_embed/models/bolts/__init__.py
bioimage_embed/models/bolts/vae.py
bioimage_embed/models/bolts/vqvae.py
bioimage_embed/models/factory.py
bioimage_embed/models/legacy/__init__.py
bioimage_embed/models/legacy/ae.py
bioimage_embed/models/legacy/resnets.py
bioimage_embed/models/legacy/utils.py
bioimage_embed/models/legacy/vae.py
bioimage_embed/models/legacy/vq_vae.py
bioimage_embed/models/mae.py
bioimage_embed/models/nets/__init__.py
bioimage_embed/models/nets/convnet.py
bioimage_embed/models/nets/resnet.py
bioimage_embed/models/pyro/vae.py
bioimage_embed/models/pythae/__init__.py
bioimage_embed/models/pythae/legacy/__init__.py
bioimage_embed/models/pythae/legacy/vq_vae.py
bioimage_embed/models/pythae/vqvae.py
bioimage_embed/models/tests/legacy.py
bioimage_embed/models/tests/mae.py
bioimage_embed/models/tests/test_factory.py
bioimage_embed/models/vit/mae/mae.py
bioimage_embed/models/vit/mae_pythae.py
bioimage_embed/models/vit/models_vit.py
bioimage_embed/models/vit/sam.py
bioimage_embed/models/vit/tests/mae.py
bioimage_embed/shapes/__init__.py
bioimage_embed/shapes/contours.py
bioimage_embed/shapes/distance_matrix_loss.py
bioimage_embed/shapes/lightning.py
bioimage_embed/shapes/loss_functions.py
bioimage_embed/shapes/mds.py
bioimage_embed/shapes/tests/test_dist_to_coord.png
bioimage_embed/shapes/tests/test_dist_to_mask.png
bioimage_embed/shapes/tests/test_generate_img_crop.png
bioimage_embed-0.1.2.dist-info/METADATA
bioimage_embed-0.1.2.dist-info/WHEEL
bioimage_embed-0.1.2.dist-info/entry_points.txt
bioimage_embed-0.1.2.dist-info/RECORD
