Metadata-Version: 2.1
Name: bioimage_embed
Version: 0.1.2
Summary: 
Author: Craig
Author-email: ctr26@ebi.ac.uk
Requires-Python: >=3.9,<3.11
Classifier: Programming Language :: Python :: 3
Classifier: Programming Language :: Python :: 3.9
Classifier: Programming Language :: Python :: 3.10
Requires-Dist: Pillow (==9.5.0)
Requires-Dist: albumentations (>=1.3.1,<2.0.0)
Requires-Dist: bokeh (>=3.2.2,<4.0.0)
Requires-Dist: colorcet (>=3.0.1,<4.0.0)
Requires-Dist: holoviews (>=1.17.1,<2.0.0)
Requires-Dist: hydra-core (>=1.3.2,<2.0.0)
Requires-Dist: ipykernel (>=6.25.1,<7.0.0)
Requires-Dist: iteround (>=1.0.4,<2.0.0)
Requires-Dist: jsonargparse[signatures] (>=4.21.0,<5.0.0)
Requires-Dist: jupyter (>=1.0.0,<2.0.0)
Requires-Dist: jupytext (>=1.16.4,<2.0.0)
Requires-Dist: lightning-bolts (>=0.7.0,<0.8.0)
Requires-Dist: llvmlite (==0.40.1)
Requires-Dist: matplotlib (>=3.7.2,<4.0.0)
Requires-Dist: monai (>=1.3.2,<2.0.0)
Requires-Dist: nonechucks (>=0.4.2,<0.5.0)
Requires-Dist: numpy (==1.23)
Requires-Dist: onnx (>=1.15.0,<2.0.0)
Requires-Dist: pandas (>=2.1.0,<3.0.0)
Requires-Dist: pip (>=23.2.1,<24.0.0)
Requires-Dist: pydantic (>=2.6.4,<3.0.0)
Requires-Dist: pyefd (>=1.6.0,<2.0.0)
Requires-Dist: pyro-ppl (>=1.8.6,<2.0.0)
Requires-Dist: pythae (>=0.1.2,<0.2.0)
Requires-Dist: pytorch-lightning (==1.*)
Requires-Dist: ray[all] (>=2.8.1,<3.0.0)
Requires-Dist: requests (>=2.31.0,<3.0.0)
Requires-Dist: scikit-image (>=0.21.0,<0.22.0)
Requires-Dist: shapely (>=2.0.1,<3.0.0)
Requires-Dist: tensorboard (>=2.14.0,<3.0.0)
Requires-Dist: tikzplotlib (>=0.10.1,<0.11.0)
Requires-Dist: timm (>=0.9.6,<0.10.0)
Requires-Dist: torch (>=2.3.1,<3.0.0)
Requires-Dist: torchinfo (>=1.8.0,<2.0.0)
Requires-Dist: torchmetrics (==0.11.4)
Requires-Dist: torchvision (>=0.18.1,<0.19.0)
Requires-Dist: transformers (>=4.42.4,<5.0.0)
Requires-Dist: typer (>=0.9.0,<0.10.0)
Requires-Dist: umap-learn[plot] (>=0.5.3,<0.6.0)
Requires-Dist: urllib3 (==2.2.2)
Requires-Dist: wandb (>=0.17.4,<0.18.0)
